{
  "Groupe Nice-Matin": {
    "domain": "###_fr_groupe_nice_matin",
    "group": [
      "monacomatin.mc",
      "nicematin.com",
      "varmatin.com"
    ],
    "allow_cookies": 1,
    "amp_unhide": 1,
    "block_regex": "(\\.poool\\.fr\\/|cdn\\.ampproject\\.org\\/v\\d\\/amp-(access|(sticky-)?ad)-.+\\.js)",
    "cs_code": [{
        "cond": "div#article-teaser",
        "rm_attrib": "id"
      }
    ]
  },
  "Il Foglio": {
    "domain": "ilfoglio.it",
    "allow_cookies": 1,
    "amp_redirect": {
      "paywall": ".paywall"
    },
    "amp_unhide": 1,
    "block_regex": "cdn\\.ampproject\\.org\\/v\\d\\/amp-((sticky-)?ad|subscriptions)-.+\\.js"
  },
  "Mainichi Shimbun": {
    "domain": "mainichi.jp",
    "allow_cookies": 1,
    "useragent": "googlebot"
  },
  "Science (free articles only)": {
    "domain": "science.org",
    "allow_cookies": 1,
    "cs_code": [{
        "cond": "div.alert-read-limit",
        "rm_elem": 1
      }, {
        "cond": "body.alert-read-limit__overlay",
        "rm_attrib": "class"
      }
    ]
  },
  "The Indian Express": {
    "domain": "indianexpress.com",
    "allow_cookies": 1,
    "block_regex": "(\\/indianexpress\\.com\\/.+\\/indianexpress\\/js\\/(evolok\\/.+|min\\/premiumContent)\\.js|cdn\\.ampproject\\.org\\/v\\d\\/amp-(access|(sticky-)?ad)-.+\\.js)"
  },
  "The New Statesman": {
    "domain": "newstatesman.com",
    "allow_cookies": 1,
    "block_regex": "\\.newstatesman\\.com\\/.+\\/nsmg-evolok-paywall\\/.+\\.js"
  },
  "Tribune Publishing Company": {
    "domain": "###_usa_tribune",
    "group": [
      "baltimoresun.com",
      "capitalgazette.com",
      "chicagotribune.com",
      "courant.com",
      "dailypress.com",
      "mcall.com",
      "nydailynews.com",
      "orlandosentinel.com",
      "pilotonline.com",
      "sun-sentinel.com"
    ],
    "allow_cookies": 1,
    "block_regex": "(\\.tribdss\\.com\\/|\\.zephr\\.com\\/zephr-browser\\/.+\\/zephr-browser\\.umd\\.js)"
  }
}
